{
  "data1": [{"open_job_number":10000, "geolocation":"San Diego", "profession_specialty":"Travel Nurser", "pay":"$2000"}],
  "data2": [{"open_job_number":1234, "geolocation":"San Diego", "profession_specialty":"Travel Nurse", "pay":"$2000"}],
  "data3": [{"open_job_number":99999, "geolocation":"San Diego", "profession_specialty":"Travel Nurse", "pay":"$2000"}],
  "data4": [
  {
"id": "401872903",
"date": "2026-05-21T00:00Z",
"game_description": "Live",
"home_id": "17",
"home_school": null,
"home_name": "New Zealand",
"away_id": "37",
"away_school": null,
"away_name": "Netherlands",
"home_logo": "https://cdn.flashtalking.com/147604/SlingWorldCup_Flags/NewZealand.png",
"away_logo": "https://cdn.flashtalking.com/147604/SlingWorldCup_Flags/Netherlands.png",
"home_color": null,
"home_secondary_color": null,
"away_color": null,
"away_secondary_color": null,
"home_score": "2",
"away_score": "1",
"home_curated_rank": null,
"away_curated_rank": null,
"gameRank": null,
"network": "ESPN",
"network_logo": "https://cdn.flashtalking.com/feeds/slingtv/FBI-8587/images/espn.png",
"clock": "10:10",
"timestamp_pretty": "Saturday, June 12 12:30 PM ET",
"quarter": "SECOND HALF",
"status": "Live",
"in_progress": true,
"schedule_day": "TODAY",
"schedule_time": "12:30 PM ET"
}
],
"data5": [  
  {
"id": "401872903",
"date": "2026-05-21T00:00Z",
"game_description": "Scheduled",
"home_id": "17",
"home_school": null,
"home_name": "New Zealand",
"away_id": "37",
"away_school": null,
"away_name": "Netherlands",
"home_logo": "https://cdn.flashtalking.com/147604/SlingWorldCup_Flags/NewZealand.png",
"away_logo": "https://cdn.flashtalking.com/147604/SlingWorldCup_Flags/Netherlands.png",
"home_color": null,
"home_secondary_color": null,
"away_color": null,
"away_secondary_color": null,
"home_score": "0",
"away_score": "0",
"home_curated_rank": null,
"away_curated_rank": null,
"gameRank": null,
"network": "ESPN",
"network_logo": "https://cdn.flashtalking.com/feeds/slingtv/FBI-8587/images/espn.png",
"clock": "0:00",
"timestamp_pretty": "Saturday, June 12 12:30 PM PST",
"quarter": 0,
"status": "Scheduled",
"in_progress": false,
"schedule_day": "SATURDAY",
"schedule_time": "12:30 PM PST"
},
  {
"id": "401872904",
"date": "2026-05-21T00:00Z",
"game_description": "Scheduled",
"home_id": "17",
"home_school": null,
"home_name": "Netherlands",
"away_id": "37",
"away_school": null,
"away_name": "New Zealand",
"home_logo": "https://cdn.flashtalking.com/147604/SlingWorldCup_Flags/Netherlands.png",
"away_logo": "https://cdn.flashtalking.com/147604/SlingWorldCup_Flags/NewZealand.png",
"home_color": null,
"home_secondary_color": null,
"away_color": null,
"away_secondary_color": null,
"home_score": "0",
"away_score": "0",
"home_curated_rank": null,
"away_curated_rank": null,
"gameRank": null,
"network": "ESPN",
"network_logo": "https://cdn.flashtalking.com/feeds/slingtv/FBI-8587/images/espn.png",
"clock": "0:00",
"timestamp_pretty": "Saturday, June 12 16:30 PM PST",
"quarter": 0,
"status": "Scheduled",
"in_progress": false,
"schedule_day": "SATURDAY",
"schedule_time": "16:30 PM PST"
},
  {
"id": "401872905",
"date": "2026-05-21T00:00Z",
"game_description": "Scheduled",
"home_id": "17",
"home_school": null,
"home_name": "New Zealand",
"away_id": "37",
"away_school": null,
"away_name": "Netherlands",
"home_logo": "https://cdn.flashtalking.com/147604/SlingWorldCup_Flags/NewZealand.png",
"away_logo": "https://cdn.flashtalking.com/147604/SlingWorldCup_Flags/Netherlands.png",
"home_color": null,
"home_secondary_color": null,
"away_color": null,
"away_secondary_color": null,
"home_score": "0",
"away_score": "0",
"home_curated_rank": null,
"away_curated_rank": null,
"gameRank": null,
"network": "ESPN",
"network_logo": "https://cdn.flashtalking.com/feeds/slingtv/FBI-8587/images/espn.png",
"clock": "0:00",
"timestamp_pretty": "Sunday, June 13 10:30 PM PST",
"quarter": 0,
"status": "Scheduled",
"in_progress": false,
"schedule_day": "SUNDAY",
"schedule_time": "20:30 PM PST"
}
]
}
